{
  "id": "Lab",
  "realm": "Lab",
  "displayName": "Lab",
  "notBefore": 0,
  "defaultSignatureAlgorithm": "RS256",
  "revokeRefreshToken": false,
  "refreshTokenMaxReuse": 0,
  "accessTokenLifespan": 300,
  "accessTokenLifespanForImplicitFlow": 900,
  "ssoSessionIdleTimeout": 1800,
  "ssoSessionMaxLifespan": 36000,
  "ssoSessionIdleTimeoutRememberMe": 0,
  "ssoSessionMaxLifespanRememberMe": 0,
  "offlineSessionIdleTimeout": 2592000,
  "offlineSessionMaxLifespanEnabled": false,
  "offlineSessionMaxLifespan": 5184000,
  "clientSessionIdleTimeout": 0,
  "clientSessionMaxLifespan": 0,
  "clientOfflineSessionIdleTimeout": 0,
  "clientOfflineSessionMaxLifespan": 0,
  "accessCodeLifespan": 60,
  "accessCodeLifespanUserAction": 300,
  "accessCodeLifespanLogin": 1800,
  "actionTokenGeneratedByAdminLifespan": 43200,
  "actionTokenGeneratedByUserLifespan": 300,
  "oauth2DeviceCodeLifespan": 600,
  "oauth2DevicePollingInterval": 5,
  "enabled": true,
  "sslRequired": "external",
  "registrationAllowed": false,
  "registrationEmailAsUsername": false,
  "rememberMe": false,
  "verifyEmail": false,
  "loginWithEmailAllowed": true,
  "duplicateEmailsAllowed": false,
  "resetPasswordAllowed": false,
  "editUsernameAllowed": false,
  "bruteForceProtected": false,
  "permanentLockout": false,
  "maxFailureWaitSeconds": 900,
  "minimumQuickLoginWaitSeconds": 60,
  "waitIncrementSeconds": 60,
  "quickLoginCheckMilliSeconds": 1000,
  "maxDeltaTimeSeconds": 43200,
  "failureFactor": 30,
  "defaultRole": {
    "id": "da8b5f64-a9f6-4634-b2a8-1c776c35728b",
    "name": "default-roles-lab",
    "description": "${role_default-roles}",
    "composite": true,
    "clientRole": false,
    "containerId": "Lab"
  },
  "requiredCredentials": [
    "password"
  ],
  "otpPolicyType": "totp",
  "otpPolicyAlgorithm": "HmacSHA1",
  "otpPolicyInitialCounter": 0,
  "otpPolicyDigits": 6,
  "otpPolicyLookAheadWindow": 1,
  "otpPolicyPeriod": 30,
  "otpSupportedApplications": [
    "FreeOTP",
    "Google Authenticator"
  ],
  "webAuthnPolicyRpEntityName": "keycloak",
  "webAuthnPolicySignatureAlgorithms": [
    "ES256"
  ],
  "webAuthnPolicyRpId": "",
  "webAuthnPolicyAttestationConveyancePreference": "not specified",
  "webAuthnPolicyAuthenticatorAttachment": "not specified",
  "webAuthnPolicyRequireResidentKey": "not specified",
  "webAuthnPolicyUserVerificationRequirement": "not specified",
  "webAuthnPolicyCreateTimeout": 0,
  "webAuthnPolicyAvoidSameAuthenticatorRegister": false,
  "webAuthnPolicyAcceptableAaguids": [],
  "webAuthnPolicyPasswordlessRpEntityName": "keycloak",
  "webAuthnPolicyPasswordlessSignatureAlgorithms": [
    "ES256"
  ],
  "webAuthnPolicyPasswordlessRpId": "",
  "webAuthnPolicyPasswordlessAttestationConveyancePreference": "not specified",
  "webAuthnPolicyPasswordlessAuthenticatorAttachment": "not specified",
  "webAuthnPolicyPasswordlessRequireResidentKey": "not specified",
  "webAuthnPolicyPasswordlessUserVerificationRequirement": "not specified",
  "webAuthnPolicyPasswordlessCreateTimeout": 0,
  "webAuthnPolicyPasswordlessAvoidSameAuthenticatorRegister": false,
  "webAuthnPolicyPasswordlessAcceptableAaguids": [],
  "scopeMappings": [
    {
      "clientScope": "offline_access",
      "roles": [
        "offline_access"
      ]
    }
  ],
  "clientScopeMappings": {
    "account": [
      {
        "client": "account-console",
        "roles": [
          "manage-account"
        ]
      }
    ]
  },
  "clients": [
    {
      "id": "cd9bd476-11ca-449b-a541-1f936d565a29",
      "clientId": "account",
      "name": "${client_account}",
      "rootUrl": "${authBaseUrl}",
      "baseUrl": "/realms/Lab/account/",
      "surrogateAuthRequired": false,
      "enabled": true,
      "alwaysDisplayInConsole": false,
      "clientAuthenticatorType": "client-secret",
      "redirectUris": [
        "/realms/Lab/account/*"
      ],
      "webOrigins": [],
      "notBefore": 0,
      "bearerOnly": false,
      "consentRequired": false,
      "standardFlowEnabled": true,
      "implicitFlowEnabled": false,
      "directAccessGrantsEnabled": false,
      "serviceAccountsEnabled": false,
      "publicClient": true,
      "frontchannelLogout": false,
      "protocol": "openid-connect",
      "attributes": {},
      "authenticationFlowBindingOverrides": {},
      "fullScopeAllowed": false,
      "nodeReRegistrationTimeout": 0,
      "defaultClientScopes": [
        "web-origins",
        "profile",
        "roles",
        "email"
      ],
      "optionalClientScopes": [
        "address",
        "phone",
        "offline_access",
        "microprofile-jwt"
      ]
    },
    {
      "id": "863145c0-1554-4baf-8556-f2e5aacb5389",
      "clientId": "account-console",
      "name": "${client_account-console}",
      "rootUrl": "${authBaseUrl}",
      "baseUrl": "/realms/lab/account/",
      "surrogateAuthRequired": false,
      "enabled": true,
      "alwaysDisplayInConsole": false,
      "clientAuthenticatorType": "client-secret",
      "redirectUris": [
        "/realms/lab/account/*"
      ],
      "webOrigins": [],
      "notBefore": 0,
      "bearerOnly": false,
      "consentRequired": false,
      "standardFlowEnabled": true,
      "implicitFlowEnabled": false,
      "directAccessGrantsEnabled": false,
      "serviceAccountsEnabled": false,
      "publicClient": true,
      "frontchannelLogout": false,
      "protocol": "openid-connect",
      "attributes": {
        "pkce.code.challenge.method": "S256"
      },
      "authenticationFlowBindingOverrides": {},
      "fullScopeAllowed": false,
      "nodeReRegistrationTimeout": 0,
      "protocolMappers": [
        {
          "id": "9d1b2915-af99-4628-af9d-980955703d57",
          "name": "audience resolve",
          "protocol": "openid-connect",
          "protocolMapper": "oidc-audience-resolve-mapper",
          "consentRequired": false,
          "config": {}
        }
      ],
      "defaultClientScopes": [
        "web-origins",
        "profile",
        "roles",
        "email"
      ],
      "optionalClientScopes": [
        "address",
        "phone",
        "offline_access",
        "microprofile-jwt"
      ]
    },
    {
      "id": "48907bb6-57ac-4587-95b7-bf002697ed97",
      "clientId": "admin-cli",
      "name": "${client_admin-cli}",
      "surrogateAuthRequired": false,
      "enabled": true,
      "alwaysDisplayInConsole": false,
      "clientAuthenticatorType": "client-secret",
      "redirectUris": [],
      "webOrigins": [],
      "notBefore": 0,
      "bearerOnly": false,
      "consentRequired": false,
      "standardFlowEnabled": false,
      "implicitFlowEnabled": false,
      "directAccessGrantsEnabled": true,
      "serviceAccountsEnabled": false,
      "publicClient": true,
      "frontchannelLogout": false,
      "protocol": "openid-connect",
      "attributes": {},
      "authenticationFlowBindingOverrides": {},
      "fullScopeAllowed": false,
      "nodeReRegistrationTimeout": 0,
      "defaultClientScopes": [
        "web-origins",
        "profile",
        "roles",
        "email"
      ],
      "optionalClientScopes": [
        "address",
        "phone",
        "offline_access",
        "microprofile-jwt"
      ]
    },
    {
      "id": "76321fab-4df4-4363-a948-6a4adae04b72",
      "clientId": "broker",
      "name": "${client_broker}",
      "surrogateAuthRequired": false,
      "enabled": true,
      "alwaysDisplayInConsole": false,
      "clientAuthenticatorType": "client-secret",
      "redirectUris": [],
      "webOrigins": [],
      "notBefore": 0,
      "bearerOnly": true,
      "consentRequired": false,
      "standardFlowEnabled": true,
      "implicitFlowEnabled": false,
      "directAccessGrantsEnabled": false,
      "serviceAccountsEnabled": false,
      "publicClient": false,
      "frontchannelLogout": false,
      "protocol": "openid-connect",
      "attributes": {},
      "authenticationFlowBindingOverrides": {},
      "fullScopeAllowed": false,
      "nodeReRegistrationTimeout": 0,
      "defaultClientScopes": [
        "web-origins",
        "profile",
        "roles",
        "email"
      ],
      "optionalClientScopes": [
        "address",
        "phone",
        "offline_access",
        "microprofile-jwt"
      ]
    },
    {
      "id": "e937cad3-8dbd-4541-8140-ef3a264fcf44",
      "clientId": "guacamole",
      "name": "guacamole",
      "rootUrl": "",
      "adminUrl": "",
      "surrogateAuthRequired": false,
      "enabled": true,
      "alwaysDisplayInConsole": false,
      "clientAuthenticatorType": "client-secret",
      "redirectUris": [
        "*"
      ],
      "webOrigins": [
        "*"
      ],
      "notBefore": 0,
      "bearerOnly": false,
      "consentRequired": false,
      "standardFlowEnabled": true,
      "implicitFlowEnabled": true,
      "directAccessGrantsEnabled": true,
      "serviceAccountsEnabled": false,
      "publicClient": true,
      "frontchannelLogout": false,
      "protocol": "openid-connect",
      "attributes": {
        "saml.assertion.signature": "false",
        "saml.force.post.binding": "false",
        "saml.multivalued.roles": "false",
        "saml.encrypt": "false",
        "backchannel.logout.revoke.offline.tokens": "false",
        "saml.server.signature": "false",
        "saml.server.signature.keyinfo.ext": "false",
        "exclude.session.state.from.auth.response": "true",
        "backchannel.logout.session.required": "true",
        "saml_force_name_id_format": "false",
        "saml.client.signature": "false",
        "tls.client.certificate.bound.access.tokens": "false",
        "saml.authnstatement": "false",
        "display.on.consent.screen": "false",
        "saml.onetimeuse.condition": "false"
      },
      "authenticationFlowBindingOverrides": {},
      "fullScopeAllowed": true,
      "nodeReRegistrationTimeout": -1,
      "defaultClientScopes": [
        "web-origins",
        "profile",
        "roles",
        "groups",
        "email"
      ],
      "optionalClientScopes": [
        "address",
        "phone",
        "offline_access",
        "microprofile-jwt"
      ]
    },
    {
      "id": "c7b1c15b-da01-40e2-b407-289bc3b2cad0",
      "clientId": "realm-management",
      "name": "${client_realm-management}",
      "surrogateAuthRequired": false,
      "enabled": true,
      "alwaysDisplayInConsole": false,
      "clientAuthenticatorType": "client-secret",
      "redirectUris": [],
      "webOrigins": [],
      "notBefore": 0,
      "bearerOnly": true,
      "consentRequired": false,
      "standardFlowEnabled": true,
      "implicitFlowEnabled": false,
      "directAccessGrantsEnabled": false,
      "serviceAccountsEnabled": false,
      "publicClient": false,
      "frontchannelLogout": false,
      "protocol": "openid-connect",
      "attributes": {},
      "authenticationFlowBindingOverrides": {},
      "fullScopeAllowed": false,
      "nodeReRegistrationTimeout": 0,
      "defaultClientScopes": [
        "web-origins",
        "profile",
        "roles",
        "email"
      ],
      "optionalClientScopes": [
        "address",
        "phone",
        "offline_access",
        "microprofile-jwt"
      ]
    },
    {
      "id": "cb4e59eb-78d8-4b93-b4d4-5f3d13f8f32a",
      "clientId": "security-admin-console",
      "name": "${client_security-admin-console}",
      "rootUrl": "${authAdminUrl}",
      "baseUrl": "/admin/Lab/console/",
      "surrogateAuthRequired": false,
      "enabled": true,
      "alwaysDisplayInConsole": false,
      "clientAuthenticatorType": "client-secret",
      "redirectUris": [
        "/admin/Lab/console/*"
      ],
      "webOrigins": [
        "+"
      ],
      "notBefore": 0,
      "bearerOnly": false,
      "consentRequired": false,
      "standardFlowEnabled": true,
      "implicitFlowEnabled": false,
      "directAccessGrantsEnabled": false,
      "serviceAccountsEnabled": false,
      "publicClient": true,
      "frontchannelLogout": false,
      "protocol": "openid-connect",
      "attributes": {
        "pkce.code.challenge.method": "S256"
      },
      "authenticationFlowBindingOverrides": {},
      "fullScopeAllowed": false,
      "nodeReRegistrationTimeout": 0,
      "protocolMappers": [
        {
          "id": "6221feda-f784-431b-b41e-2f2e23ad00b9",
          "name": "locale",
          "protocol": "openid-connect",
          "protocolMapper": "oidc-usermodel-attribute-mapper",
          "consentRequired": false,
          "config": {
            "userinfo.token.claim": "true",
            "user.attribute": "locale",
            "id.token.claim": "true",
            "access.token.claim": "true",
            "claim.name": "locale",
            "jsonType.label": "String"
          }
        }
      ],
      "defaultClientScopes": [
        "web-origins",
        "profile",
        "roles",
        "email"
      ],
      "optionalClientScopes": [
        "address",
        "phone",
        "offline_access",
        "microprofile-jwt"
      ]
    }
  ],
  "clientScopes": [
    {
      "id": "884e4bbd-e293-4972-9905-d2581b193a51",
      "name": "offline_access",
      "description": "OpenID Connect built-in scope: offline_access",
      "protocol": "openid-connect",
      "attributes": {
        "consent.screen.text": "${offlineAccessScopeConsentText}",
        "display.on.consent.screen": "true"
      }
    },
    {
      "id": "78481a10-83c1-41c6-bcd4-447d40dfb2e8",
      "name": "profile",
      "description": "OpenID Connect built-in scope: profile",
      "protocol": "openid-connect",
      "attributes": {
        "include.in.token.scope": "true",
        "display.on.consent.screen": "true",
        "consent.screen.text": "${profileScopeConsentText}"
      },
      "protocolMappers": [
        {
          "id": "b15afd84-0ea1-4b01-9809-a16a4d3b9ddc",
          "name": "gender",
          "protocol": "openid-connect",
          "protocolMapper": "oidc-usermodel-attribute-mapper",
          "consentRequired": false,
          "config": {
            "userinfo.token.claim": "true",
            "user.attribute": "gender",
            "id.token.claim": "true",
            "access.token.claim": "true",
            "claim.name": "gender",
            "jsonType.label": "String"
          }
        },
        {
          "id": "4ffc5f2e-ef56-4b61-9b30-34f0ca478520",
          "name": "nickname",
          "protocol": "openid-connect",
          "protocolMapper": "oidc-usermodel-attribute-mapper",
          "consentRequired": false,
          "config": {
            "userinfo.token.claim": "true",
            "user.attribute": "nickname",
            "id.token.claim": "true",
            "access.token.claim": "true",
            "claim.name": "nickname",
            "jsonType.label": "String"
          }
        },
        {
          "id": "7e7fa174-240a-426f-92cd-aa4b7b5f1e78",
          "name": "birthdate",
          "protocol": "openid-connect",
          "protocolMapper": "oidc-usermodel-attribute-mapper",
          "consentRequired": false,
          "config": {
            "userinfo.token.claim": "true",
            "user.attribute": "birthdate",
            "id.token.claim": "true",
            "access.token.claim": "true",
            "claim.name": "birthdate",
            "jsonType.label": "String"
          }
        },
        {
          "id": "4c45e2b9-9133-43e6-9027-0f32d7cc9bd9",
          "name": "profile",
          "protocol": "openid-connect",
          "protocolMapper": "oidc-usermodel-attribute-mapper",
          "consentRequired": false,
          "config": {
            "userinfo.token.claim": "true",
            "user.attribute": "profile",
            "id.token.claim": "true",
            "access.token.claim": "true",
            "claim.name": "profile",
            "jsonType.label": "String"
          }
        },
        {
          "id": "ae13392c-55ea-404d-89d2-ea7fcb596291",
          "name": "zoneinfo",
          "protocol": "openid-connect",
          "protocolMapper": "oidc-usermodel-attribute-mapper",
          "consentRequired": false,
          "config": {
            "userinfo.token.claim": "true",
            "user.attribute": "zoneinfo",
            "id.token.claim": "true",
            "access.token.claim": "true",
            "claim.name": "zoneinfo",
            "jsonType.label": "String"
          }
        },
        {
          "id": "4e74b958-e232-4214-9347-a60d574e0d3c",
          "name": "website",
          "protocol": "openid-connect",
          "protocolMapper": "oidc-usermodel-attribute-mapper",
          "consentRequired": false,
          "config": {
            "userinfo.token.claim": "true",
            "user.attribute": "website",
            "id.token.claim": "true",
            "access.token.claim": "true",
            "claim.name": "website",
            "jsonType.label": "String"
          }
        },
        {
          "id": "0aa24f29-8c67-4b11-b049-337525bf5de6",
          "name": "middle name",
          "protocol": "openid-connect",
          "protocolMapper": "oidc-usermodel-attribute-mapper",
          "consentRequired": false,
          "config": {
            "userinfo.token.claim": "true",
            "user.attribute": "middleName",
            "id.token.claim": "true",
            "access.token.claim": "true",
            "claim.name": "middle_name",
            "jsonType.label": "String"
          }
        },
        {
          "id": "d13667fd-0ae5-42cd-9f60-bab8a7e98ced",
          "name": "picture",
          "protocol": "openid-connect",
          "protocolMapper": "oidc-usermodel-attribute-mapper",
          "consentRequired": false,
          "config": {
            "userinfo.token.claim": "true",
            "user.attribute": "picture",
            "id.token.claim": "true",
            "access.token.claim": "true",
            "claim.name": "picture",
            "jsonType.label": "String"
          }
        },
        {
          "id": "b2eac285-a435-49a6-8e07-6e522307daf3",
          "name": "family name",
          "protocol": "openid-connect",
          "protocolMapper": "oidc-usermodel-property-mapper",
          "consentRequired": false,
          "config": {
            "userinfo.token.claim": "true",
            "user.attribute": "lastName",
            "id.token.claim": "true",
            "access.token.claim": "true",
            "claim.name": "family_name",
            "jsonType.label": "String"
          }
        },
        {
          "id": "99ce8694-465f-41a8-a6a4-d629a04e91ef",
          "name": "full name",
          "protocol": "openid-connect",
          "protocolMapper": "oidc-full-name-mapper",
          "consentRequired": false,
          "config": {
            "id.token.claim": "true",
            "access.token.claim": "true",
            "userinfo.token.claim": "true"
          }
        },
        {
          "id": "dc001959-e142-4386-a4ec-9582add564af",
          "name": "locale",
          "protocol": "openid-connect",
          "protocolMapper": "oidc-usermodel-attribute-mapper",
          "consentRequired": false,
          "config": {
            "userinfo.token.claim": "true",
            "user.attribute": "locale",
            "id.token.claim": "true",
            "access.token.claim": "true",
            "claim.name": "locale",
            "jsonType.label": "String"
          }
        },
        {
          "id": "b4e6f3c8-7b77-45c6-ac1d-be9c0908d9d5",
          "name": "updated at",
          "protocol": "openid-connect",
          "protocolMapper": "oidc-usermodel-attribute-mapper",
          "consentRequired": false,
          "config": {
            "userinfo.token.claim": "true",
            "user.attribute": "updatedAt",
            "id.token.claim": "true",
            "access.token.claim": "true",
            "claim.name": "updated_at",
            "jsonType.label": "String"
          }
        },
        {
          "id": "d2ecc84f-cb5b-4b57-bc40-d4803050cce8",
          "name": "username",
          "protocol": "openid-connect",
          "protocolMapper": "oidc-usermodel-property-mapper",
          "consentRequired": false,
          "config": {
            "userinfo.token.claim": "true",
            "user.attribute": "username",
            "id.token.claim": "true",
            "access.token.claim": "true",
            "claim.name": "preferred_username",
            "jsonType.label": "String"
          }
        },
        {
          "id": "562a4589-3cb0-4cfb-83fb-94adf521ef04",
          "name": "given name",
          "protocol": "openid-connect",
          "protocolMapper": "oidc-usermodel-property-mapper",
          "consentRequired": false,
          "config": {
            "userinfo.token.claim": "true",
            "user.attribute": "firstName",
            "id.token.claim": "true",
            "access.token.claim": "true",
            "claim.name": "given_name",
            "jsonType.label": "String"
          }
        }
      ]
    },
    {
      "id": "32c664e8-1ce3-49ca-992a-b79c00058668",
      "name": "address",
      "description": "OpenID Connect built-in scope: address",
      "protocol": "openid-connect",
      "attributes": {
        "include.in.token.scope": "true",
        "display.on.consent.screen": "true",
        "consent.screen.text": "${addressScopeConsentText}"
      },
      "protocolMappers": [
        {
          "id": "35ffc817-fe5f-4e4a-935c-a4eb3fb7c29d",
          "name": "address",
          "protocol": "openid-connect",
          "protocolMapper": "oidc-address-mapper",
          "consentRequired": false,
          "config": {
            "user.attribute.formatted": "formatted",
            "user.attribute.country": "country",
            "user.attribute.postal_code": "postal_code",
            "userinfo.token.claim": "true",
            "user.attribute.street": "street",
            "id.token.claim": "true",
            "user.attribute.region": "region",
            "access.token.claim": "true",
            "user.attribute.locality": "locality"
          }
        }
      ]
    },
    {
      "id": "e65a53ca-39a3-4cd1-8671-8d600464df03",
      "name": "groups",
      "protocol": "openid-connect",
      "attributes": {
        "include.in.token.scope": "true",
        "display.on.consent.screen": "true"
      },
      "protocolMappers": [
        {
          "id": "790182fc-55ef-4250-8584-bda074184d26",
          "name": "groups",
          "protocol": "openid-connect",
          "protocolMapper": "oidc-group-membership-mapper",
          "consentRequired": false,
          "config": {
            "full.path": "false",
            "id.token.claim": "true",
            "access.token.claim": "true",
            "claim.name": "groups",
            "userinfo.token.claim": "true"
          }
        }
      ]
    },
    {
      "id": "73e7d643-01ed-44d2-955c-f88d69510c9f",
      "name": "web-origins",
      "description": "OpenID Connect scope for add allowed web origins to the access token",
      "protocol": "openid-connect",
      "attributes": {
        "include.in.token.scope": "false",
        "display.on.consent.screen": "false",
        "consent.screen.text": ""
      },
      "protocolMappers": [
        {
          "id": "d9f81d06-0982-4e08-add8-c4a3f2664931",
          "name": "allowed web origins",
          "protocol": "openid-connect",
          "protocolMapper": "oidc-allowed-origins-mapper",
          "consentRequired": false,
          "config": {}
        }
      ]
    },
    {
      "id": "b8edcfae-fd56-4b66-8972-0f6d09b67d8e",
      "name": "microprofile-jwt",
      "description": "Microprofile - JWT built-in scope",
      "protocol": "openid-connect",
      "attributes": {
        "include.in.token.scope": "true",
        "display.on.consent.screen": "false"
      },
      "protocolMappers": [
        {
          "id": "f8d0f2ed-1ee5-48b7-a432-75c6333d63ac",
          "name": "upn",
          "protocol": "openid-connect",
          "protocolMapper": "oidc-usermodel-property-mapper",
          "consentRequired": false,
          "config": {
            "userinfo.token.claim": "true",
            "user.attribute": "username",
            "id.token.claim": "true",
            "access.token.claim": "true",
            "claim.name": "upn",
            "jsonType.label": "String"
          }
        },
        {
          "id": "dc171db6-a68e-422e-b2db-81d18414a8e2",
          "name": "groups",
          "protocol": "openid-connect",
          "protocolMapper": "oidc-usermodel-realm-role-mapper",
          "consentRequired": false,
          "config": {
            "multivalued": "true",
            "userinfo.token.claim": "true",
            "user.attribute": "foo",
            "id.token.claim": "true",
            "access.token.claim": "true",
            "claim.name": "groups",
            "jsonType.label": "String"
          }
        }
      ]
    },
    {
      "id": "ec851a59-3c72-4004-a46d-63f14feb04c3",
      "name": "roles",
      "description": "OpenID Connect scope for add user roles to the access token",
      "protocol": "openid-connect",
      "attributes": {
        "include.in.token.scope": "false",
        "display.on.consent.screen": "true",
        "consent.screen.text": "${rolesScopeConsentText}"
      },
      "protocolMappers": [
        {
          "id": "f433c82e-6fea-4583-a156-58ad7325aa59",
          "name": "audience resolve",
          "protocol": "openid-connect",
          "protocolMapper": "oidc-audience-resolve-mapper",
          "consentRequired": false,
          "config": {}
        },
        {
          "id": "08b40402-50bf-4b16-a69f-b4d5919f0551",
          "name": "client roles",
          "protocol": "openid-connect",
          "protocolMapper": "oidc-usermodel-client-role-mapper",
          "consentRequired": false,
          "config": {
            "user.attribute": "foo",
            "access.token.claim": "true",
            "claim.name": "resource_access.${client_id}.roles",
            "jsonType.label": "String",
            "multivalued": "true"
          }
        },
        {
          "id": "d710e659-86bf-4b81-896a-ce4ea71647b1",
          "name": "realm roles",
          "protocol": "openid-connect",
          "protocolMapper": "oidc-usermodel-realm-role-mapper",
          "consentRequired": false,
          "config": {
            "user.attribute": "foo",
            "access.token.claim": "true",
            "claim.name": "realm_access.roles",
            "jsonType.label": "String",
            "multivalued": "true"
          }
        }
      ]
    },
    {
      "id": "e43934dd-d9e6-4f51-a519-6448fe25b284",
      "name": "email",
      "description": "OpenID Connect built-in scope: email",
      "protocol": "openid-connect",
      "attributes": {
        "include.in.token.scope": "true",
        "display.on.consent.screen": "true",
        "consent.screen.text": "${emailScopeConsentText}"
      },
      "protocolMappers": [
        {
          "id": "4095fe9a-ebbe-4001-8ea7-ec7f034b4ba9",
          "name": "email verified",
          "protocol": "openid-connect",
          "protocolMapper": "oidc-usermodel-property-mapper",
          "consentRequired": false,
          "config": {
            "userinfo.token.claim": "true",
            "user.attribute": "emailVerified",
            "id.token.claim": "true",
            "access.token.claim": "true",
            "claim.name": "email_verified",
            "jsonType.label": "boolean"
          }
        },
        {
          "id": "a78e2934-e737-42bd-84b4-92125d413ddc",
          "name": "email",
          "protocol": "openid-connect",
          "protocolMapper": "oidc-usermodel-property-mapper",
          "consentRequired": false,
          "config": {
            "userinfo.token.claim": "true",
            "user.attribute": "email",
            "id.token.claim": "true",
            "access.token.claim": "true",
            "claim.name": "email",
            "jsonType.label": "String"
          }
        }
      ]
    },
    {
      "id": "3f41b09d-293e-4247-b1cc-15ca9a4a6859",
      "name": "role_list",
      "description": "SAML role list",
      "protocol": "saml",
      "attributes": {
        "consent.screen.text": "${samlRoleListScopeConsentText}",
        "display.on.consent.screen": "true"
      },
      "protocolMappers": [
        {
          "id": "44a0636e-af4a-4e6d-8ddd-33ed448e465a",
          "name": "role list",
          "protocol": "saml",
          "protocolMapper": "saml-role-list-mapper",
          "consentRequired": false,
          "config": {
            "single": "false",
            "attribute.nameformat": "Basic",
            "attribute.name": "Role"
          }
        }
      ]
    },
    {
      "id": "d4736e06-a8cf-41a4-94ac-9083438a333b",
      "name": "phone",
      "description": "OpenID Connect built-in scope: phone",
      "protocol": "openid-connect",
      "attributes": {
        "include.in.token.scope": "true",
        "display.on.consent.screen": "true",
        "consent.screen.text": "${phoneScopeConsentText}"
      },
      "protocolMappers": [
        {
          "id": "b714d0c8-40f6-4a1e-9072-7d59c75f4c69",
          "name": "phone number verified",
          "protocol": "openid-connect",
          "protocolMapper": "oidc-usermodel-attribute-mapper",
          "consentRequired": false,
          "config": {
            "userinfo.token.claim": "true",
            "user.attribute": "phoneNumberVerified",
            "id.token.claim": "true",
            "access.token.claim": "true",
            "claim.name": "phone_number_verified",
            "jsonType.label": "boolean"
          }
        },
        {
          "id": "7443d770-60ce-48da-ac90-a952379cce56",
          "name": "phone number",
          "protocol": "openid-connect",
          "protocolMapper": "oidc-usermodel-attribute-mapper",
          "consentRequired": false,
          "config": {
            "userinfo.token.claim": "true",
            "user.attribute": "phoneNumber",
            "id.token.claim": "true",
            "access.token.claim": "true",
            "claim.name": "phone_number",
            "jsonType.label": "String"
          }
        }
      ]
    }
  ],
  "defaultDefaultClientScopes": [
    "role_list",
    "profile",
    "email",
    "roles",
    "web-origins"
  ],
  "defaultOptionalClientScopes": [
    "offline_access",
    "address",
    "phone",
    "microprofile-jwt"
  ],
  "browserSecurityHeaders": {
    "contentSecurityPolicyReportOnly": "",
    "xContentTypeOptions": "nosniff",
    "xRobotsTag": "none",
    "xFrameOptions": "SAMEORIGIN",
    "contentSecurityPolicy": "frame-src 'self'; frame-ancestors 'self'; object-src 'none';",
    "xXSSProtection": "1; mode=block",
    "strictTransportSecurity": "max-age=31536000; includeSubDomains"
  },
  "smtpServer": {
    "host": "email.winllc-dev.com",
    "from": "dave@winllc-dev.com",
    "starttls": "",
    "auth": "",
    "ssl": ""
  },
  "loginTheme": "Otp-Login",
  "emailTheme": "Otp-Login",
  "eventsEnabled": false,
  "eventsListeners": [
    "jboss-logging"
  ],
  "enabledEventTypes": [],
  "adminEventsEnabled": false,
  "adminEventsDetailsEnabled": false,
  "identityProviders": [],
  "identityProviderMappers": [],
  "components": {
    "org.keycloak.services.clientregistration.policy.ClientRegistrationPolicy": [
      {
        "id": "9b9efe17-aee0-4987-b220-62ad43f3d6bc",
        "name": "Allowed Protocol Mapper Types",
        "providerId": "allowed-protocol-mappers",
        "subType": "anonymous",
        "subComponents": {},
        "config": {
          "allowed-protocol-mapper-types": [
            "saml-user-attribute-mapper",
            "oidc-usermodel-property-mapper",
            "oidc-sha256-pairwise-sub-mapper",
            "oidc-usermodel-attribute-mapper",
            "saml-role-list-mapper",
            "saml-user-property-mapper",
            "oidc-address-mapper",
            "oidc-full-name-mapper"
          ]
        }
      },
      {
        "id": "741cdb7a-46c3-4f5e-8cf4-8c0a37d443d0",
        "name": "Allowed Client Scopes",
        "providerId": "allowed-client-templates",
        "subType": "authenticated",
        "subComponents": {},
        "config": {
          "allow-default-scopes": [
            "true"
          ]
        }
      },
      {
        "id": "8f98b530-b342-42ed-a414-662d83c05561",
        "name": "Max Clients Limit",
        "providerId": "max-clients",
        "subType": "anonymous",
        "subComponents": {},
        "config": {
          "max-clients": [
            "200"
          ]
        }
      },
      {
        "id": "1c913f14-5cf6-4df8-b5f5-e8d734f14d52",
        "name": "Consent Required",
        "providerId": "consent-required",
        "subType": "anonymous",
        "subComponents": {},
        "config": {}
      },
      {
        "id": "a1346005-d01c-47ef-98ac-ebca763d1b8a",
        "name": "Allowed Client Scopes",
        "providerId": "allowed-client-templates",
        "subType": "anonymous",
        "subComponents": {},
        "config": {
          "allow-default-scopes": [
            "true"
          ]
        }
      },
      {
        "id": "b2188fb7-3b6a-4400-bb2a-089b23061f4f",
        "name": "Full Scope Disabled",
        "providerId": "scope",
        "subType": "anonymous",
        "subComponents": {},
        "config": {}
      },
      {
        "id": "7ce60b76-83a9-4672-ac8f-8de00b182ca2",
        "name": "Trusted Hosts",
        "providerId": "trusted-hosts",
        "subType": "anonymous",
        "subComponents": {},
        "config": {
          "host-sending-registration-request-must-match": [
            "true"
          ],
          "client-uris-must-match": [
            "true"
          ]
        }
      },
      {
        "id": "c7755b0b-cde2-47c5-9ea7-2309201a98cb",
        "name": "Allowed Protocol Mapper Types",
        "providerId": "allowed-protocol-mappers",
        "subType": "authenticated",
        "subComponents": {},
        "config": {
          "allowed-protocol-mapper-types": [
            "oidc-full-name-mapper",
            "saml-user-attribute-mapper",
            "oidc-usermodel-property-mapper",
            "saml-role-list-mapper",
            "oidc-usermodel-attribute-mapper",
            "oidc-address-mapper",
            "saml-user-property-mapper",
            "oidc-sha256-pairwise-sub-mapper"
          ]
        }
      }
    ],
    "org.keycloak.storage.UserStorageProvider": [
      {
        "id": "b0027637-1f76-45b1-ba98-51833385fda2",
        "name": "WINLLC Active Directory",
        "providerId": "ldap",
        "subComponents": {
          "org.keycloak.storage.ldap.mappers.LDAPStorageMapper": [
            {
              "id": "8e30fce6-4bbc-457f-a723-f67516c8da39",
              "name": "creation date",
              "providerId": "user-attribute-ldap-mapper",
              "subComponents": {},
              "config": {
                "ldap.attribute": [
                  "whenCreated"
                ],
                "is.mandatory.in.ldap": [
                  "false"
                ],
                "always.read.value.from.ldap": [
                  "true"
                ],
                "read.only": [
                  "true"
                ],
                "user.model.attribute": [
                  "createTimestamp"
                ]
              }
            },
            {
              "id": "1f6fa49b-5f62-428b-9685-6d0b44e40e0c",
              "name": "username",
              "providerId": "user-attribute-ldap-mapper",
              "subComponents": {},
              "config": {
                "ldap.attribute": [
                  "sAMAccountName"
                ],
                "is.mandatory.in.ldap": [
                  "true"
                ],
                "read.only": [
                  "false"
                ],
                "always.read.value.from.ldap": [
                  "false"
                ],
                "user.model.attribute": [
                  "username"
                ]
              }
            },
            {
              "id": "a44c8af9-bd9e-4c33-94a6-e9d7ff29314c",
              "name": "MSAD account controls",
              "providerId": "msad-user-account-control-mapper",
              "subComponents": {},
              "config": {}
            },
            {
              "id": "d5132427-621d-4dc0-ad34-3a2da7784a43",
              "name": "email",
              "providerId": "user-attribute-ldap-mapper",
              "subComponents": {},
              "config": {
                "ldap.attribute": [
                  "mail"
                ],
                "is.mandatory.in.ldap": [
                  "false"
                ],
                "always.read.value.from.ldap": [
                  "false"
                ],
                "read.only": [
                  "false"
                ],
                "user.model.attribute": [
                  "email"
                ]
              }
            },
            {
              "id": "dca28568-b040-4663-be98-49c7029635da",
              "name": "modify date",
              "providerId": "user-attribute-ldap-mapper",
              "subComponents": {},
              "config": {
                "ldap.attribute": [
                  "whenChanged"
                ],
                "is.mandatory.in.ldap": [
                  "false"
                ],
                "read.only": [
                  "true"
                ],
                "always.read.value.from.ldap": [
                  "true"
                ],
                "user.model.attribute": [
                  "modifyTimestamp"
                ]
              }
            },
            {
              "id": "6813da44-f4c2-4cf7-8002-04ce5a573944",
              "name": "username-cn",
              "providerId": "user-attribute-ldap-mapper",
              "subComponents": {},
              "config": {
                "ldap.attribute": [
                  "cn"
                ],
                "is.mandatory.in.ldap": [
                  "true"
                ],
                "always.read.value.from.ldap": [
                  "false"
                ],
                "read.only": [
                  "false"
                ],
                "user.model.attribute": [
                  "username"
                ]
              }
            },
            {
              "id": "6017c07b-5181-4fcf-b345-4083dd057462",
              "name": "groups",
              "providerId": "group-ldap-mapper",
              "subComponents": {},
              "config": {
                "membership.attribute.type": [
                  "DN"
                ],
                "group.name.ldap.attribute": [
                  "cn"
                ],
                "membership.user.ldap.attribute": [
                  "sAMAccountName"
                ],
                "preserve.group.inheritance": [
                  "false"
                ],
                "groups.dn": [
                  "CN=Users,DC=winllc-dev,DC=com"
                ],
                "mode": [
                  "LDAP_ONLY"
                ],
                "user.roles.retrieve.strategy": [
                  "LOAD_GROUPS_BY_MEMBER_ATTRIBUTE"
                ],
                "ignore.missing.groups": [
                  "true"
                ],
                "membership.ldap.attribute": [
                  "member"
                ],
                "group.object.classes": [
                  "group"
                ],
                "memberof.ldap.attribute": [
                  "memberOf"
                ],
                "drop.non.existing.groups.during.sync": [
                  "true"
                ],
                "groups.path": [
                  "/"
                ]
              }
            },
            {
              "id": "3fae3f44-d4c2-4c11-9e04-90c2909f6ed5",
              "name": "first name",
              "providerId": "user-attribute-ldap-mapper",
              "subComponents": {},
              "config": {
                "ldap.attribute": [
                  "givenName"
                ],
                "is.mandatory.in.ldap": [
                  "true"
                ],
                "always.read.value.from.ldap": [
                  "true"
                ],
                "read.only": [
                  "false"
                ],
                "user.model.attribute": [
                  "firstName"
                ]
              }
            },
            {
              "id": "bbf9f350-6739-4f3f-b92f-b306d7265c6f",
              "name": "last name",
              "providerId": "user-attribute-ldap-mapper",
              "subComponents": {},
              "config": {
                "ldap.attribute": [
                  "sn"
                ],
                "is.mandatory.in.ldap": [
                  "true"
                ],
                "read.only": [
                  "false"
                ],
                "always.read.value.from.ldap": [
                  "true"
                ],
                "user.model.attribute": [
                  "lastName"
                ]
              }
            }
          ]
        },
        "config": {
          "fullSyncPeriod": [
            "-1"
          ],
          "pagination": [
            "true"
          ],
          "connectionPooling": [
            "true"
          ],
          "usersDn": [
            "cn=Users,dc=winllc-dev,dc=com"
          ],
          "cachePolicy": [
            "DEFAULT"
          ],
          "useKerberosForPasswordAuthentication": [
            "false"
          ],
          "importEnabled": [
            "true"
          ],
          "enabled": [
            "true"
          ],
          "changedSyncPeriod": [
            "-1"
          ],
          "bindCredential": [
            "**********"
          ],
          "usernameLDAPAttribute": [
            "sAMAccountName"
          ],
          "bindDn": [
            "CN=keycloak admin,CN=Managed Service Accounts,DC=winllc-dev,DC=com"
          ],
          "lastSync": [
            "1639483043"
          ],
          "vendor": [
            "ad"
          ],
          "uuidLDAPAttribute": [
            "objectGUID"
          ],
          "allowKerberosAuthentication": [
            "false"
          ],
          "connectionUrl": [
            "ldaps://WIN-225FIT514GG.winllc-dev.com:636"
          ],
          "syncRegistrations": [
            "false"
          ],
          "authType": [
            "simple"
          ],
          "debug": [
            "false"
          ],
          "searchScope": [
            "1"
          ],
          "useTruststoreSpi": [
            "ldapsOnly"
          ],
          "priority": [
            "0"
          ],
          "trustEmail": [
            "false"
          ],
          "userObjectClasses": [
            "person, organizationalPerson, user"
          ],
          "rdnLDAPAttribute": [
            "cn"
          ],
          "editMode": [
            "WRITABLE"
          ],
          "validatePasswordPolicy": [
            "false"
          ],
          "batchSizeForSync": [
            "1000"
          ]
        }
      }
    ],
    "org.keycloak.userprofile.UserProfileProvider": [
      {
        "id": "8a19d012-5b88-4920-a435-443d5585b9da",
        "providerId": "declarative-user-profile",
        "subComponents": {},
        "config": {}
      }
    ],
    "org.keycloak.keys.KeyProvider": [
      {
        "id": "2396d1b6-a447-4742-a8d4-d18dbead840b",
        "name": "hmac-generated",
        "providerId": "hmac-generated",
        "subComponents": {},
        "config": {
          "priority": [
            "100"
          ],
          "algorithm": [
            "HS256"
          ]
        }
      },
      {
        "id": "63c0b47a-72d3-4ac3-a4f6-a2badd83dc21",
        "name": "rsa-enc-generated",
        "providerId": "rsa-generated",
        "subComponents": {},
        "config": {
          "keyUse": [
            "enc"
          ],
          "priority": [
            "100"
          ]
        }
      },
      {
        "id": "86bbbc9a-72fe-47b0-a0a1-677afad5028f",
        "name": "rsa-generated",
        "providerId": "rsa-generated",
        "subComponents": {},
        "config": {
          "keyUse": [
            "sig"
          ],
          "priority": [
            "100"
          ]
        }
      },
      {
        "id": "2bf18498-9996-434b-b4db-96a2975c89bf",
        "name": "aes-generated",
        "providerId": "aes-generated",
        "subComponents": {},
        "config": {
          "priority": [
            "100"
          ]
        }
      }
    ]
  },
  "internationalizationEnabled": true,
  "supportedLocales": [
    "en"
  ],
  "defaultLocale": "en",
  "authenticationFlows": [
    {
      "id": "f41f76bc-9274-4e88-99b8-a2b786a0797b",
      "alias": "Account verification options",
      "description": "Method with which to verity the existing account",
      "providerId": "basic-flow",
      "topLevel": false,
      "builtIn": true,
      "authenticationExecutions": [
        {
          "authenticator": "idp-email-verification",
          "authenticatorFlow": false,
          "requirement": "ALTERNATIVE",
          "priority": 10,
          "userSetupAllowed": false,
          "autheticatorFlow": false
        },
        {
          "authenticatorFlow": true,
          "requirement": "ALTERNATIVE",
          "priority": 20,
          "flowAlias": "Verify Existing Account by Re-authentication",
          "userSetupAllowed": false,
          "autheticatorFlow": true
        }
      ]
    },
    {
      "id": "c3c7d899-78f0-433e-bfde-b94e1354a1e9",
      "alias": "Authentication Options",
      "description": "Authentication options.",
      "providerId": "basic-flow",
      "topLevel": false,
      "builtIn": true,
      "authenticationExecutions": [
        {
          "authenticator": "basic-auth",
          "authenticatorFlow": false,
          "requirement": "REQUIRED",
          "priority": 10,
          "userSetupAllowed": false,
          "autheticatorFlow": false
        },
        {
          "authenticator": "basic-auth-otp",
          "authenticatorFlow": false,
          "requirement": "DISABLED",
          "priority": 20,
          "userSetupAllowed": false,
          "autheticatorFlow": false
        },
        {
          "authenticator": "auth-spnego",
          "authenticatorFlow": false,
          "requirement": "DISABLED",
          "priority": 30,
          "userSetupAllowed": false,
          "autheticatorFlow": false
        }
      ]
    },
    {
      "id": "34445669-92b5-4a82-a89b-dcd387d4cd6d",
      "alias": "Browser - Conditional OTP",
      "description": "Flow to determine if the OTP is required for the authentication",
      "providerId": "basic-flow",
      "topLevel": false,
      "builtIn": true,
      "authenticationExecutions": [
        {
          "authenticator": "conditional-user-configured",
          "authenticatorFlow": false,
          "requirement": "REQUIRED",
          "priority": 10,
          "userSetupAllowed": false,
          "autheticatorFlow": false
        },
        {
          "authenticator": "auth-otp-form",
          "authenticatorFlow": false,
          "requirement": "REQUIRED",
          "priority": 20,
          "userSetupAllowed": false,
          "autheticatorFlow": false
        }
      ]
    },
    {
      "id": "9fc19cb8-6cc5-4631-b4ff-7f6f7635d237",
      "alias": "Browser and OTP",
      "description": "browser based authentication",
      "providerId": "basic-flow",
      "topLevel": true,
      "builtIn": false,
      "authenticationExecutions": [
        {
          "authenticator": "auth-cookie",
          "authenticatorFlow": false,
          "requirement": "ALTERNATIVE",
          "priority": 10,
          "userSetupAllowed": false,
          "autheticatorFlow": false
        },
        {
          "authenticator": "auth-spnego",
          "authenticatorFlow": false,
          "requirement": "DISABLED",
          "priority": 20,
          "userSetupAllowed": false,
          "autheticatorFlow": false
        },
        {
          "authenticator": "identity-provider-redirector",
          "authenticatorFlow": false,
          "requirement": "ALTERNATIVE",
          "priority": 25,
          "userSetupAllowed": false,
          "autheticatorFlow": false
        },
        {
          "authenticatorFlow": true,
          "requirement": "ALTERNATIVE",
          "priority": 30,
          "flowAlias": "Browser and OTP forms",
          "userSetupAllowed": false,
          "autheticatorFlow": true
        }
      ]
    },
    {
      "id": "bdbacb7a-828b-40b6-9885-213e8fc68efd",
      "alias": "Browser and OTP Browser - Conditional OTP",
      "description": "Flow to determine if the OTP is required for the authentication",
      "providerId": "basic-flow",
      "topLevel": false,
      "builtIn": false,
      "authenticationExecutions": [
        {
          "authenticator": "conditional-user-configured",
          "authenticatorFlow": false,
          "requirement": "REQUIRED",
          "priority": 10,
          "userSetupAllowed": false,
          "autheticatorFlow": false
        },
        {
          "authenticator": "keycloak-otp-login",
          "authenticatorFlow": false,
          "requirement": "REQUIRED",
          "priority": 11,
          "userSetupAllowed": false,
          "autheticatorFlow": false
        }
      ]
    },
    {
      "id": "05dac46d-2e4c-4928-9122-b0b8de76fa82",
      "alias": "Browser and OTP forms",
      "description": "Username, password, otp and other auth forms.",
      "providerId": "basic-flow",
      "topLevel": false,
      "builtIn": false,
      "authenticationExecutions": [
        {
          "authenticator": "auth-username-password-form",
          "authenticatorFlow": false,
          "requirement": "REQUIRED",
          "priority": 10,
          "userSetupAllowed": false,
          "autheticatorFlow": false
        },
        {
          "authenticatorFlow": true,
          "requirement": "REQUIRED",
          "priority": 20,
          "flowAlias": "Browser and OTP Browser - Conditional OTP",
          "userSetupAllowed": false,
          "autheticatorFlow": true
        }
      ]
    },
    {
      "id": "025960c5-60db-4eaa-ae75-ac06386a6948",
      "alias": "Direct Grant - Conditional OTP",
      "description": "Flow to determine if the OTP is required for the authentication",
      "providerId": "basic-flow",
      "topLevel": false,
      "builtIn": true,
      "authenticationExecutions": [
        {
          "authenticator": "conditional-user-configured",
          "authenticatorFlow": false,
          "requirement": "REQUIRED",
          "priority": 10,
          "userSetupAllowed": false,
          "autheticatorFlow": false
        },
        {
          "authenticator": "direct-grant-validate-otp",
          "authenticatorFlow": false,
          "requirement": "REQUIRED",
          "priority": 20,
          "userSetupAllowed": false,
          "autheticatorFlow": false
        }
      ]
    },
    {
      "id": "01064df6-aac4-41b8-9e56-81b16f994762",
      "alias": "First broker login - Conditional OTP",
      "description": "Flow to determine if the OTP is required for the authentication",
      "providerId": "basic-flow",
      "topLevel": false,
      "builtIn": true,
      "authenticationExecutions": [
        {
          "authenticator": "conditional-user-configured",
          "authenticatorFlow": false,
          "requirement": "REQUIRED",
          "priority": 10,
          "userSetupAllowed": false,
          "autheticatorFlow": false
        },
        {
          "authenticator": "auth-otp-form",
          "authenticatorFlow": false,
          "requirement": "REQUIRED",
          "priority": 20,
          "userSetupAllowed": false,
          "autheticatorFlow": false
        }
      ]
    },
    {
      "id": "632016e8-2f01-4b6a-b648-7c9300c10b93",
      "alias": "Handle Existing Account",
      "description": "Handle what to do if there is existing account with same email/username like authenticated identity provider",
      "providerId": "basic-flow",
      "topLevel": false,
      "builtIn": true,
      "authenticationExecutions": [
        {
          "authenticator": "idp-confirm-link",
          "authenticatorFlow": false,
          "requirement": "REQUIRED",
          "priority": 10,
          "userSetupAllowed": false,
          "autheticatorFlow": false
        },
        {
          "authenticatorFlow": true,
          "requirement": "REQUIRED",
          "priority": 20,
          "flowAlias": "Account verification options",
          "userSetupAllowed": false,
          "autheticatorFlow": true
        }
      ]
    },
    {
      "id": "c93ff76c-d632-4438-a16c-e2721f9ce0d7",
      "alias": "Reset - Conditional OTP",
      "description": "Flow to determine if the OTP should be reset or not. Set to REQUIRED to force.",
      "providerId": "basic-flow",
      "topLevel": false,
      "builtIn": true,
      "authenticationExecutions": [
        {
          "authenticator": "conditional-user-configured",
          "authenticatorFlow": false,
          "requirement": "REQUIRED",
          "priority": 10,
          "userSetupAllowed": false,
          "autheticatorFlow": false
        },
        {
          "authenticator": "reset-otp",
          "authenticatorFlow": false,
          "requirement": "REQUIRED",
          "priority": 20,
          "userSetupAllowed": false,
          "autheticatorFlow": false
        }
      ]
    },
    {
      "id": "5de78453-d4ce-4ce2-b195-eb48a2d54f12",
      "alias": "User creation or linking",
      "description": "Flow for the existing/non-existing user alternatives",
      "providerId": "basic-flow",
      "topLevel": false,
      "builtIn": true,
      "authenticationExecutions": [
        {
          "authenticatorConfig": "create unique user config",
          "authenticator": "idp-create-user-if-unique",
          "authenticatorFlow": false,
          "requirement": "ALTERNATIVE",
          "priority": 10,
          "userSetupAllowed": false,
          "autheticatorFlow": false
        },
        {
          "authenticatorFlow": true,
          "requirement": "ALTERNATIVE",
          "priority": 20,
          "flowAlias": "Handle Existing Account",
          "userSetupAllowed": false,
          "autheticatorFlow": true
        }
      ]
    },
    {
      "id": "fcf0b67e-647c-4ba1-89e4-a78195923274",
      "alias": "Verify Existing Account by Re-authentication",
      "description": "Reauthentication of existing account",
      "providerId": "basic-flow",
      "topLevel": false,
      "builtIn": true,
      "authenticationExecutions": [
        {
          "authenticator": "idp-username-password-form",
          "authenticatorFlow": false,
          "requirement": "REQUIRED",
          "priority": 10,
          "userSetupAllowed": false,
          "autheticatorFlow": false
        },
        {
          "authenticatorFlow": true,
          "requirement": "CONDITIONAL",
          "priority": 20,
          "flowAlias": "First broker login - Conditional OTP",
          "userSetupAllowed": false,
          "autheticatorFlow": true
        }
      ]
    },
    {
      "id": "318e325d-903d-4207-9490-7f845ca227fe",
      "alias": "browser",
      "description": "browser based authentication",
      "providerId": "basic-flow",
      "topLevel": true,
      "builtIn": true,
      "authenticationExecutions": [
        {
          "authenticator": "auth-cookie",
          "authenticatorFlow": false,
          "requirement": "ALTERNATIVE",
          "priority": 10,
          "userSetupAllowed": false,
          "autheticatorFlow": false
        },
        {
          "authenticator": "auth-spnego",
          "authenticatorFlow": false,
          "requirement": "DISABLED",
          "priority": 20,
          "userSetupAllowed": false,
          "autheticatorFlow": false
        },
        {
          "authenticator": "identity-provider-redirector",
          "authenticatorFlow": false,
          "requirement": "ALTERNATIVE",
          "priority": 25,
          "userSetupAllowed": false,
          "autheticatorFlow": false
        },
        {
          "authenticatorFlow": true,
          "requirement": "ALTERNATIVE",
          "priority": 30,
          "flowAlias": "forms",
          "userSetupAllowed": false,
          "autheticatorFlow": true
        }
      ]
    },
    {
      "id": "957654b1-da68-4a9a-9449-2797a22801bf",
      "alias": "clients",
      "description": "Base authentication for clients",
      "providerId": "client-flow",
      "topLevel": true,
      "builtIn": true,
      "authenticationExecutions": [
        {
          "authenticator": "client-secret",
          "authenticatorFlow": false,
          "requirement": "ALTERNATIVE",
          "priority": 10,
          "userSetupAllowed": false,
          "autheticatorFlow": false
        },
        {
          "authenticator": "client-jwt",
          "authenticatorFlow": false,
          "requirement": "ALTERNATIVE",
          "priority": 20,
          "userSetupAllowed": false,
          "autheticatorFlow": false
        },
        {
          "authenticator": "client-secret-jwt",
          "authenticatorFlow": false,
          "requirement": "ALTERNATIVE",
          "priority": 30,
          "userSetupAllowed": false,
          "autheticatorFlow": false
        },
        {
          "authenticator": "client-x509",
          "authenticatorFlow": false,
          "requirement": "ALTERNATIVE",
          "priority": 40,
          "userSetupAllowed": false,
          "autheticatorFlow": false
        }
      ]
    },
    {
      "id": "1379eaea-236e-4e02-8e14-2dc630e21f23",
      "alias": "direct grant",
      "description": "OpenID Connect Resource Owner Grant",
      "providerId": "basic-flow",
      "topLevel": true,
      "builtIn": true,
      "authenticationExecutions": [
        {
          "authenticator": "direct-grant-validate-username",
          "authenticatorFlow": false,
          "requirement": "REQUIRED",
          "priority": 10,
          "userSetupAllowed": false,
          "autheticatorFlow": false
        },
        {
          "authenticator": "direct-grant-validate-password",
          "authenticatorFlow": false,
          "requirement": "REQUIRED",
          "priority": 20,
          "userSetupAllowed": false,
          "autheticatorFlow": false
        },
        {
          "authenticatorFlow": true,
          "requirement": "CONDITIONAL",
          "priority": 30,
          "flowAlias": "Direct Grant - Conditional OTP",
          "userSetupAllowed": false,
          "autheticatorFlow": true
        }
      ]
    },
    {
      "id": "42e13496-f349-406a-8777-859bc741ed99",
      "alias": "docker auth",
      "description": "Used by Docker clients to authenticate against the IDP",
      "providerId": "basic-flow",
      "topLevel": true,
      "builtIn": true,
      "authenticationExecutions": [
        {
          "authenticator": "docker-http-basic-authenticator",
          "authenticatorFlow": false,
          "requirement": "REQUIRED",
          "priority": 10,
          "userSetupAllowed": false,
          "autheticatorFlow": false
        }
      ]
    },
    {
      "id": "9e532468-d5a8-497b-8c9f-258463f2195d",
      "alias": "first broker login",
      "description": "Actions taken after first broker login with identity provider account, which is not yet linked to any Keycloak account",
      "providerId": "basic-flow",
      "topLevel": true,
      "builtIn": true,
      "authenticationExecutions": [
        {
          "authenticatorConfig": "review profile config",
          "authenticator": "idp-review-profile",
          "authenticatorFlow": false,
          "requirement": "REQUIRED",
          "priority": 10,
          "userSetupAllowed": false,
          "autheticatorFlow": false
        },
        {
          "authenticatorFlow": true,
          "requirement": "REQUIRED",
          "priority": 20,
          "flowAlias": "User creation or linking",
          "userSetupAllowed": false,
          "autheticatorFlow": true
        }
      ]
    },
    {
      "id": "79cb457c-d1a6-46a3-9793-3118a0786ab1",
      "alias": "forms",
      "description": "Username, password, otp and other auth forms.",
      "providerId": "basic-flow",
      "topLevel": false,
      "builtIn": true,
      "authenticationExecutions": [
        {
          "authenticator": "auth-username-password-form",
          "authenticatorFlow": false,
          "requirement": "REQUIRED",
          "priority": 10,
          "userSetupAllowed": false,
          "autheticatorFlow": false
        },
        {
          "authenticatorFlow": true,
          "requirement": "CONDITIONAL",
          "priority": 20,
          "flowAlias": "Browser - Conditional OTP",
          "userSetupAllowed": false,
          "autheticatorFlow": true
        }
      ]
    },
    {
      "id": "32a6da67-b9c0-43f3-a202-fd77debbc5a9",
      "alias": "http challenge",
      "description": "An authentication flow based on challenge-response HTTP Authentication Schemes",
      "providerId": "basic-flow",
      "topLevel": true,
      "builtIn": true,
      "authenticationExecutions": [
        {
          "authenticator": "no-cookie-redirect",
          "authenticatorFlow": false,
          "requirement": "REQUIRED",
          "priority": 10,
          "userSetupAllowed": false,
          "autheticatorFlow": false
        },
        {
          "authenticatorFlow": true,
          "requirement": "REQUIRED",
          "priority": 20,
          "flowAlias": "Authentication Options",
          "userSetupAllowed": false,
          "autheticatorFlow": true
        }
      ]
    },
    {
      "id": "560b1c20-ef70-4b78-9dbc-18984ee175ae",
      "alias": "registration",
      "description": "registration flow",
      "providerId": "basic-flow",
      "topLevel": true,
      "builtIn": true,
      "authenticationExecutions": [
        {
          "authenticator": "registration-page-form",
          "authenticatorFlow": true,
          "requirement": "REQUIRED",
          "priority": 10,
          "flowAlias": "registration form",
          "userSetupAllowed": false,
          "autheticatorFlow": true
        }
      ]
    },
    {
      "id": "38156131-c29e-4724-a83f-68e0712f444f",
      "alias": "registration form",
      "description": "registration form",
      "providerId": "form-flow",
      "topLevel": false,
      "builtIn": true,
      "authenticationExecutions": [
        {
          "authenticator": "registration-user-creation",
          "authenticatorFlow": false,
          "requirement": "REQUIRED",
          "priority": 20,
          "userSetupAllowed": false,
          "autheticatorFlow": false
        },
        {
          "authenticator": "registration-profile-action",
          "authenticatorFlow": false,
          "requirement": "REQUIRED",
          "priority": 40,
          "userSetupAllowed": false,
          "autheticatorFlow": false
        },
        {
          "authenticator": "registration-password-action",
          "authenticatorFlow": false,
          "requirement": "REQUIRED",
          "priority": 50,
          "userSetupAllowed": false,
          "autheticatorFlow": false
        },
        {
          "authenticator": "registration-recaptcha-action",
          "authenticatorFlow": false,
          "requirement": "DISABLED",
          "priority": 60,
          "userSetupAllowed": false,
          "autheticatorFlow": false
        }
      ]
    },
    {
      "id": "6536ba45-39b1-48b2-bbaa-85fb7927bf67",
      "alias": "reset credentials",
      "description": "Reset credentials for a user if they forgot their password or something",
      "providerId": "basic-flow",
      "topLevel": true,
      "builtIn": true,
      "authenticationExecutions": [
        {
          "authenticator": "reset-credentials-choose-user",
          "authenticatorFlow": false,
          "requirement": "REQUIRED",
          "priority": 10,
          "userSetupAllowed": false,
          "autheticatorFlow": false
        },
        {
          "authenticator": "reset-credential-email",
          "authenticatorFlow": false,
          "requirement": "REQUIRED",
          "priority": 20,
          "userSetupAllowed": false,
          "autheticatorFlow": false
        },
        {
          "authenticator": "reset-password",
          "authenticatorFlow": false,
          "requirement": "REQUIRED",
          "priority": 30,
          "userSetupAllowed": false,
          "autheticatorFlow": false
        },
        {
          "authenticatorFlow": true,
          "requirement": "CONDITIONAL",
          "priority": 40,
          "flowAlias": "Reset - Conditional OTP",
          "userSetupAllowed": false,
          "autheticatorFlow": true
        }
      ]
    },
    {
      "id": "ace983cd-bc13-4b4e-b010-c65d7a936428",
      "alias": "saml ecp",
      "description": "SAML ECP Profile Authentication Flow",
      "providerId": "basic-flow",
      "topLevel": true,
      "builtIn": true,
      "authenticationExecutions": [
        {
          "authenticator": "http-basic-authenticator",
          "authenticatorFlow": false,
          "requirement": "REQUIRED",
          "priority": 10,
          "userSetupAllowed": false,
          "autheticatorFlow": false
        }
      ]
    }
  ],
  "authenticatorConfig": [
    {
      "id": "bf350b64-2132-4f26-bc6d-f96e5ad146e0",
      "alias": "create unique user config",
      "config": {
        "require.password.update.after.registration": "false"
      }
    },
    {
      "id": "d0d094d0-c2d9-4516-b4f1-b8052c8f4cf9",
      "alias": "review profile config",
      "config": {
        "update.profile.on.first.login": "missing"
      }
    }
  ],
  "requiredActions": [
    {
      "alias": "CONFIGURE_TOTP",
      "name": "Configure OTP",
      "providerId": "CONFIGURE_TOTP",
      "enabled": true,
      "defaultAction": false,
      "priority": 10,
      "config": {}
    },
    {
      "alias": "terms_and_conditions",
      "name": "Terms and Conditions",
      "providerId": "terms_and_conditions",
      "enabled": false,
      "defaultAction": false,
      "priority": 20,
      "config": {}
    },
    {
      "alias": "UPDATE_PASSWORD",
      "name": "Update Password",
      "providerId": "UPDATE_PASSWORD",
      "enabled": true,
      "defaultAction": false,
      "priority": 30,
      "config": {}
    },
    {
      "alias": "UPDATE_PROFILE",
      "name": "Update Profile",
      "providerId": "UPDATE_PROFILE",
      "enabled": true,
      "defaultAction": false,
      "priority": 40,
      "config": {}
    },
    {
      "alias": "VERIFY_EMAIL",
      "name": "Verify Email",
      "providerId": "VERIFY_EMAIL",
      "enabled": true,
      "defaultAction": false,
      "priority": 50,
      "config": {}
    },
    {
      "alias": "delete_account",
      "name": "Delete Account",
      "providerId": "delete_account",
      "enabled": false,
      "defaultAction": false,
      "priority": 60,
      "config": {}
    },
    {
      "alias": "update_user_locale",
      "name": "Update User Locale",
      "providerId": "update_user_locale",
      "enabled": true,
      "defaultAction": false,
      "priority": 1000,
      "config": {}
    }
  ],
  "browserFlow": "Browser and OTP",
  "registrationFlow": "registration",
  "directGrantFlow": "direct grant",
  "resetCredentialsFlow": "reset credentials",
  "clientAuthenticationFlow": "clients",
  "dockerAuthenticationFlow": "docker auth",
  "attributes": {
    "cibaBackchannelTokenDeliveryMode": "poll",
    "cibaExpiresIn": "120",
    "cibaAuthRequestedUserHint": "login_hint",
    "oauth2DeviceCodeLifespan": "600",
    "clientOfflineSessionMaxLifespan": "0",
    "oauth2DevicePollingInterval": "5",
    "clientSessionIdleTimeout": "0",
    "userProfileEnabled": "false",
    "clientSessionMaxLifespan": "0",
    "parRequestUriLifespan": "60",
    "clientOfflineSessionIdleTimeout": "0",
    "cibaInterval": "5"
  },
  "keycloakVersion": "15.0.2",
  "userManagedAccessAllowed": false,
  "clientProfiles": {
    "profiles": []
  },
  "clientPolicies": {
    "policies": []
  }
}
